{
  "schemaVersion": "1.0.0",
  "app": {
    "version": "0.3.1",
    "commit": "b86af65e3230",
    "buildTime": "2026-07-15T09:31:34.508Z",
    "sha256": "5f95bbba48497ca7d4262dbcfbdf0e07df60b0bcacc46e4d181adaaa060622bf",
    "downloadUrl": "https://github.com/energychain/Szenarienrechner-EOG/releases/latest",
    "changelogUrl": "https://github.com/energychain/Szenarienrechner-EOG/blob/main/CHANGELOG.md",
    "minSupportedVersion": "0.3.0"
  },
  "ruleset": {
    "id": "regulatory-parameters-2026-07",
    "effectiveMonth": "2026-07",
    "confidence": "consultation",
    "sourceRef": "BNetzA Anreizregulierung/ARegV/KANU sowie NEST/RAMEN-Kontext, Arbeitsstand 2026-07; pruefpflichtiger Planungsstand.",
    "changelogUrl": "https://github.com/energychain/Szenarienrechner-EOG/blob/main/REGULATORY_ASSUMPTIONS.md"
  },
  "history": [],
  "advisories": []
}
